<notation-declaration n="76"><univ bound-var="𝔉"><conditional><consequent><conditional><consequent><leaf><fa><functor><bound-var>𝔉</bound-var></functor><arg><var>y</var></arg></fa></leaf></consequent><antecedent><univ bound-var="𝔞"><conditional><consequent><leaf><fa><functor><bound-var>𝔉</bound-var></functor><arg><bound-var>𝔞</bound-var></arg></fa></leaf></consequent><antecedent><leaf><fa><functor><var>f</var></functor><arg><var>x</var></arg><arg><bound-var>𝔞</bound-var></arg></fa></leaf></antecedent></conditional></univ></antecedent></conditional></consequent><antecedent><leaf><is-inherited><property>𝔉</property><function><var>f</var></function><dummy-var>δ</dummy-var><dummy-var>α</dummy-var><order-argument>1</order-argument></is-inherited></leaf></antecedent></conditional></univ><new-notation><follows><var>x</var><var>y</var><function><var>f</var></function><dummy-var>γ</dummy-var><dummy-var>β</dummy-var></follows></new-notation></notation-declaration>
